setup.py
distributions/Binomialdistribution.py
distributions/Gaussiandistribution.py
distributions/Generaldistribution.py
distributions/__init__.py
nat_test_distributions.egg-info/PKG-INFO
nat_test_distributions.egg-info/SOURCES.txt
nat_test_distributions.egg-info/dependency_links.txt
nat_test_distributions.egg-info/not-zip-safe
nat_test_distributions.egg-info/top_level.txt